ansys/api/dyna/VERSION
ansys/api/dyna/__init__.py
ansys/api/dyna/py.typed
ansys/api/dyna/v0/dynaprocess.proto
ansys/api/dyna/v0/dynaprocess_pb2.py
ansys/api/dyna/v0/dynaprocess_pb2.pyi
ansys/api/dyna/v0/dynaprocess_pb2_grpc.py
ansys/api/dyna/v0/dynaprocess_pb2_grpc.pyi
ansys/api/dyna/v0/dynasolver.proto
ansys/api/dyna/v0/dynasolver_pb2.py
ansys/api/dyna/v0/dynasolver_pb2.pyi
ansys/api/dyna/v0/dynasolver_pb2_grpc.py
ansys/api/dyna/v0/dynasolver_pb2_grpc.pyi
ansys/api/dyna/v0/kwprocess.proto
ansys/api/dyna/v0/kwprocess_pb2.py
ansys/api/dyna/v0/kwprocess_pb2.pyi
ansys/api/dyna/v0/kwprocess_pb2_grpc.py
ansys/api/dyna/v0/kwprocess_pb2_grpc.pyi
ansys_api_dyna-0.4.2.dist-info/LICENSE
ansys_api_dyna-0.4.2.dist-info/METADATA
ansys_api_dyna-0.4.2.dist-info/WHEEL
ansys_api_dyna-0.4.2.dist-info/entry_points.txt
ansys_api_dyna-0.4.2.dist-info/top_level.txt
ansys_api_dyna-0.4.2.dist-info/RECORD
