Metadata-Version: 2.1
Name: ansys-api-dyna
Version: 0.4.2
Summary: Autogenerated python gRPC interface package for ansys-api-dyna, built on 07:27:38 on 29 November 2024
Home-page: https://github.com/ansys/ansys-api-dyna
Author: ANSYS, Inc.
Author-email: pyansys.core@ansys.com
License: MIT
Requires-Python: >=3.7
License-File: LICENSE
Requires-Dist: grpcio~=1.17
Requires-Dist: protobuf<6,>=3.19
